[
    {
        "title": "個股：中石化標售高雄亞灣區兩筆土地，處分收益5.8億元，挹注EPS 0.18元",
        "content": "\n\n \n【往下看更多】\r\n            ►外資狂砍500億 史上第6大！ 金管會喊話：大家要有信心\r\n            ►信義區「饗饗」爆確診足跡！急禁內用11天 匡列122人\r\n            ►外資挺友達上看29元 分析師揭關鍵數字：Q4當心\n",
        "keywords": [
            "東森財經",
            "fnc",
            "財經新聞",
            "股動錢潮",
            "盤前早報",
            "盤前分析",
            "東森財經新聞",
            "財經粉絲團",
            "趨勢",
            "投顧",
            "即時指數",
            "台股",
            "美股",
            "汽車",
            "房產",
            "理財",
            "投資",
            "職場",
            "產業",
            "EBC",
            "東森電視"
        ],
        "category": "stock",
        "media": "東森財經新聞",
        "datetime": "2021/08/19 10:05",
        "link": "https://fnc.ebc.net.tw/fncnews/stock/139191"
    },
    {
        "title": "產業：歐美報復性消費＋國際油價漲，紡織業大利多，化纖報價釀新一波漲勢",
        "content": "\n\n \n【往下看更多】\r\n            ►興櫃：凱勝綠能(2246)與麥格理資本簽訂MOU，攜手打造台灣綠能產業\r\n            ►產業：高解析LED顯示螢幕普及，今年全球顯示螢幕LED封裝市場規模估增12%\r\n            ►興櫃：2020東京帕運會24日登場，愛爾達取得總代理，為台灣首次帕運轉播\n",
        "keywords": [
            "東森財經",
            "fnc",
            "財經新聞",
            "股動錢潮",
            "盤前早報",
            "盤前分析",
            "東森財經新聞",
            "財經粉絲團",
            "趨勢",
            "投顧",
            "即時指數",
            "台股",
            "美股",
            "汽車",
            "房產",
            "理財",
            "投資",
            "職場",
            "產業",
            "EBC",
            "東森電視"
        ],
        "category": "else",
        "media": "東森財經新聞",
        "datetime": "2021/06/03 14:05",
        "link": "https://fnc.ebc.net.tw/fncnews/else/135466"
    },
    {
        "title": "個股：五鼎(1733)Q1業績亮眼，估Q2小蹲、Q3再跳，全年拚成長",
        "content": "\n\n \n【往下看更多】\r\n            ►外資狂砍500億 史上第6大！ 金管會喊話：大家要有信心\r\n            ►信義區「饗饗」爆確診足跡！急禁內用11天 匡列122人\r\n            ►外資挺友達上看29元 分析師揭關鍵數字：Q4當心\n",
        "keywords": [
            "東森財經",
            "fnc",
            "財經新聞",
            "股動錢潮",
            "盤前早報",
            "盤前分析",
            "東森財經新聞",
            "財經粉絲團",
            "趨勢",
            "投顧",
            "即時指數",
            "台股",
            "美股",
            "汽車",
            "房產",
            "理財",
            "投資",
            "職場",
            "產業",
            "EBC",
            "東森電視"
        ],
        "category": "stock",
        "media": "東森財經新聞",
        "datetime": "2021/04/23 14:05",
        "link": "https://fnc.ebc.net.tw/fncnews/stock/133449"
    },
    {
        "title": "個股：大億通過配1.3元現金股利，獲美國新車款訂單，H2營運可望優於H1",
        "content": "\n\n \n【往下看更多】\r\n            ►外資狂砍500億 史上第6大！ 金管會喊話：大家要有信心\r\n            ►信義區「饗饗」爆確診足跡！急禁內用11天 匡列122人\r\n            ►外資挺友達上看29元 分析師揭關鍵數字：Q4當心\n",
        "keywords": [
            "東森財經",
            "fnc",
            "財經新聞",
            "股動錢潮",
            "盤前早報",
            "盤前分析",
            "東森財經新聞",
            "財經粉絲團",
            "趨勢",
            "投顧",
            "即時指數",
            "台股",
            "美股",
            "汽車",
            "房產",
            "理財",
            "投資",
            "職場",
            "產業",
            "EBC",
            "東森電視"
        ],
        "category": "stock",
        "media": "東森財經新聞",
        "datetime": "2021/08/04 12:05",
        "link": "https://fnc.ebc.net.tw/fncnews/stock/138476"
    },
    {
        "title": "個股：廣達股息入袋，鼎天(3306)Q2獲利躍升，接單熱絡，Q3營收衝4億",
        "content": "\n\n \n【往下看更多】\r\n            ►外資狂砍500億 史上第6大！ 金管會喊話：大家要有信心\r\n            ►信義區「饗饗」爆確診足跡！急禁內用11天 匡列122人\r\n            ►外資挺友達上看29元 分析師揭關鍵數字：Q4當心\n",
        "keywords": [
            "東森財經",
            "fnc",
            "財經新聞",
            "股動錢潮",
            "盤前早報",
            "盤前分析",
            "東森財經新聞",
            "財經粉絲團",
            "趨勢",
            "投顧",
            "即時指數",
            "台股",
            "美股",
            "汽車",
            "房產",
            "理財",
            "投資",
            "職場",
            "產業",
            "EBC",
            "東森電視"
        ],
        "category": "stock",
        "media": "東森財經新聞",
        "datetime": "2021/08/03 13:05",
        "link": "https://fnc.ebc.net.tw/fncnews/stock/138423"
    },
    {
        "title": "個股：和泰車上半年每股大賺16.76元，啟動全員調薪2.85%，調幅高於同業",
        "content": "\n\n \n【往下看更多】\r\n            ►外資狂砍500億 史上第6大！ 金管會喊話：大家要有信心\r\n            ►信義區「饗饗」爆確診足跡！急禁內用11天 匡列122人\r\n            ►外資挺友達上看29元 分析師揭關鍵數字：Q4當心\n",
        "keywords": [
            "東森財經",
            "fnc",
            "財經新聞",
            "股動錢潮",
            "盤前早報",
            "盤前分析",
            "東森財經新聞",
            "財經粉絲團",
            "趨勢",
            "投顧",
            "即時指數",
            "台股",
            "美股",
            "汽車",
            "房產",
            "理財",
            "投資",
            "職場",
            "產業",
            "EBC",
            "東森電視"
        ],
        "category": "stock",
        "media": "東森財經新聞",
        "datetime": "2021/08/13 10:05",
        "link": "https://fnc.ebc.net.tw/fncnews/stock/138924"
    },
    {
        "title": "個股：劍麟(2228)Q2轉虧為盈，上半年每股盈餘2.22元",
        "content": "\n\n \n【往下看更多】\r\n            ►外資狂砍500億 史上第6大！ 金管會喊話：大家要有信心\r\n            ►信義區「饗饗」爆確診足跡！急禁內用11天 匡列122人\r\n            ►外資挺友達上看29元 分析師揭關鍵數字：Q4當心\n",
        "keywords": [
            "東森財經",
            "fnc",
            "財經新聞",
            "股動錢潮",
            "盤前早報",
            "盤前分析",
            "東森財經新聞",
            "財經粉絲團",
            "趨勢",
            "投顧",
            "即時指數",
            "台股",
            "美股",
            "汽車",
            "房產",
            "理財",
            "投資",
            "職場",
            "產業",
            "EBC",
            "東森電視"
        ],
        "category": "stock",
        "media": "東森財經新聞",
        "datetime": "2021/08/05 09:05",
        "link": "https://fnc.ebc.net.tw/fncnews/stock/138514"
    },
    {
        "title": "個股：矽晶圓報價Q3調漲，幅度達兩位數，台勝科因需求強勁投資百億擴產",
        "content": "\n\n \n【往下看更多】\r\n            ►外資狂砍500億 史上第6大！ 金管會喊話：大家要有信心\r\n            ►信義區「饗饗」爆確診足跡！急禁內用11天 匡列122人\r\n            ►外資挺友達上看29元 分析師揭關鍵數字：Q4當心\n",
        "keywords": [
            "東森財經",
            "fnc",
            "財經新聞",
            "股動錢潮",
            "盤前早報",
            "盤前分析",
            "東森財經新聞",
            "財經粉絲團",
            "趨勢",
            "投顧",
            "即時指數",
            "台股",
            "美股",
            "汽車",
            "房產",
            "理財",
            "投資",
            "職場",
            "產業",
            "EBC",
            "東森電視"
        ],
        "category": "stock",
        "media": "東森財經新聞",
        "datetime": "2021/08/03 14:05",
        "link": "https://fnc.ebc.net.tw/fncnews/stock/138428"
    },
    {
        "title": "個股：旭然(4556)越南廠首季裝機完成，今年營運增添動能",
        "content": "\n\n \n【往下看更多】\r\n            ►外資狂砍500億 史上第6大！ 金管會喊話：大家要有信心\r\n            ►信義區「饗饗」爆確診足跡！急禁內用11天 匡列122人\r\n            ►外資挺友達上看29元 分析師揭關鍵數字：Q4當心\n",
        "keywords": [
            "東森財經",
            "fnc",
            "財經新聞",
            "股動錢潮",
            "盤前早報",
            "盤前分析",
            "東森財經新聞",
            "財經粉絲團",
            "趨勢",
            "投顧",
            "即時指數",
            "台股",
            "美股",
            "汽車",
            "房產",
            "理財",
            "投資",
            "職場",
            "產業",
            "EBC",
            "東森電視"
        ],
        "category": "stock",
        "media": "東森財經新聞",
        "datetime": "2021/02/20 11:05",
        "link": "https://fnc.ebc.net.tw/fncnews/stock/131444"
    },
    {
        "title": "個股：達興材料(5234)台中新廠延至年底投產，搶攻半導體先進材料供應",
        "content": "\n\n \n【往下看更多】\r\n            ►外資狂砍500億 史上第6大！ 金管會喊話：大家要有信心\r\n            ►信義區「饗饗」爆確診足跡！急禁內用11天 匡列122人\r\n            ►外資挺友達上看29元 分析師揭關鍵數字：Q4當心\n",
        "keywords": [
            "東森財經",
            "fnc",
            "財經新聞",
            "股動錢潮",
            "盤前早報",
            "盤前分析",
            "東森財經新聞",
            "財經粉絲團",
            "趨勢",
            "投顧",
            "即時指數",
            "台股",
            "美股",
            "汽車",
            "房產",
            "理財",
            "投資",
            "職場",
            "產業",
            "EBC",
            "東森電視"
        ],
        "category": "stock",
        "media": "東森財經新聞",
        "datetime": "2021/07/22 10:05",
        "link": "https://fnc.ebc.net.tw/fncnews/stock/137836"
    }
]
