[
    {
        "title": "個股：信紘科在手訂單量創新高，台積電Fab18 b完工在即，注入成長新動能",
        "content": "\n\n \n【往下看更多】\r\n            ►小學生也瘋買股？超狂「家長會長獎」送0050 李兆華大讚\r\n            ►傳台積電加入搶櫃行列 陽明：全力配合重大業務\r\n            ►台股強彈399點該跑？專家曝「3變數」：應適時減碼\n",
        "keywords": [
            "東森財經",
            "fnc",
            "財經新聞",
            "股動錢潮",
            "盤前早報",
            "盤前分析",
            "東森財經新聞",
            "財經粉絲團",
            "趨勢",
            "投顧",
            "即時指數",
            "台股",
            "美股",
            "汽車",
            "房產",
            "理財",
            "投資",
            "職場",
            "產業",
            "EBC",
            "東森電視"
        ],
        "category": "stock",
        "media": "東森財經新聞",
        "datetime": "2021/08/16 13:05",
        "link": "https://fnc.ebc.net.tw/fncnews/stock/139019"
    },
    {
        "title": "個股：力致(3483)TGP下半年放量，單季業績拚新高",
        "content": "\n\n \n【往下看更多】\r\n            ►小學生也瘋買股？超狂「家長會長獎」送0050 李兆華大讚\r\n            ►傳台積電加入搶櫃行列 陽明：全力配合重大業務\r\n            ►台股強彈399點該跑？專家曝「3變數」：應適時減碼\n",
        "keywords": [
            "東森財經",
            "fnc",
            "財經新聞",
            "股動錢潮",
            "盤前早報",
            "盤前分析",
            "東森財經新聞",
            "財經粉絲團",
            "趨勢",
            "投顧",
            "即時指數",
            "台股",
            "美股",
            "汽車",
            "房產",
            "理財",
            "投資",
            "職場",
            "產業",
            "EBC",
            "東森電視"
        ],
        "category": "stock",
        "media": "東森財經新聞",
        "datetime": "2021/07/20 09:05",
        "link": "https://fnc.ebc.net.tw/fncnews/stock/137688"
    },
    {
        "title": "產業：歐美報復性消費＋國際油價漲，紡織業大利多，化纖報價釀新一波漲勢",
        "content": "\n\n \n【往下看更多】\r\n            ►全民上戰場就能贏？退役美軍士官憂：國軍訓練仍在1970水準\r\n            ►產業：BDI指數衝上4000大關，激勵散裝族群盤中大漲，新興、裕民等個股漲停\r\n            ►興櫃：北極星藥業-KY(6550)將啟動全球首個基因標記肝癌三期臨床試驗\n",
        "keywords": [
            "東森財經",
            "fnc",
            "財經新聞",
            "股動錢潮",
            "盤前早報",
            "盤前分析",
            "東森財經新聞",
            "財經粉絲團",
            "趨勢",
            "投顧",
            "即時指數",
            "台股",
            "美股",
            "汽車",
            "房產",
            "理財",
            "投資",
            "職場",
            "產業",
            "EBC",
            "東森電視"
        ],
        "category": "else",
        "media": "東森財經新聞",
        "datetime": "2021/06/03 14:05",
        "link": "https://fnc.ebc.net.tw/fncnews/else/135466"
    },
    {
        "title": "個股：中石化標售高雄亞灣區兩筆土地，處分收益5.8億元，挹注EPS 0.18元",
        "content": "\n\n \n【往下看更多】\r\n            ►小學生也瘋買股？超狂「家長會長獎」送0050 李兆華大讚\r\n            ►傳台積電加入搶櫃行列 陽明：全力配合重大業務\r\n            ►台股強彈399點該跑？專家曝「3變數」：應適時減碼\n",
        "keywords": [
            "東森財經",
            "fnc",
            "財經新聞",
            "股動錢潮",
            "盤前早報",
            "盤前分析",
            "東森財經新聞",
            "財經粉絲團",
            "趨勢",
            "投顧",
            "即時指數",
            "台股",
            "美股",
            "汽車",
            "房產",
            "理財",
            "投資",
            "職場",
            "產業",
            "EBC",
            "東森電視"
        ],
        "category": "stock",
        "media": "東森財經新聞",
        "datetime": "2021/08/19 10:05",
        "link": "https://fnc.ebc.net.tw/fncnews/stock/139191"
    },
    {
        "title": "個股：大銀微系統(4576)早盤順利填息，看好下半年及明年展望",
        "content": "\n\n \n【往下看更多】\r\n            ►小學生也瘋買股？超狂「家長會長獎」送0050 李兆華大讚\r\n            ►傳台積電加入搶櫃行列 陽明：全力配合重大業務\r\n            ►台股強彈399點該跑？專家曝「3變數」：應適時減碼\n",
        "keywords": [
            "東森財經",
            "fnc",
            "財經新聞",
            "股動錢潮",
            "盤前早報",
            "盤前分析",
            "東森財經新聞",
            "財經粉絲團",
            "趨勢",
            "投顧",
            "即時指數",
            "台股",
            "美股",
            "汽車",
            "房產",
            "理財",
            "投資",
            "職場",
            "產業",
            "EBC",
            "東森電視"
        ],
        "category": "stock",
        "media": "東森財經新聞",
        "datetime": "2021/08/20 10:05",
        "link": "https://fnc.ebc.net.tw/fncnews/stock/139259"
    },
    {
        "title": "個股：葉垂景稱錸德轉型走向新藍海，AD成長優於預期，明年營收占比逾1成",
        "content": "\n\n \n【往下看更多】\r\n            ►小學生也瘋買股？超狂「家長會長獎」送0050 李兆華大讚\r\n            ►傳台積電加入搶櫃行列 陽明：全力配合重大業務\r\n            ►台股強彈399點該跑？專家曝「3變數」：應適時減碼\n",
        "keywords": [
            "東森財經",
            "fnc",
            "財經新聞",
            "股動錢潮",
            "盤前早報",
            "盤前分析",
            "東森財經新聞",
            "財經粉絲團",
            "趨勢",
            "投顧",
            "即時指數",
            "台股",
            "美股",
            "汽車",
            "房產",
            "理財",
            "投資",
            "職場",
            "產業",
            "EBC",
            "東森電視"
        ],
        "category": "stock",
        "media": "東森財經新聞",
        "datetime": "2018/12/21 10:05",
        "link": "https://fnc.ebc.net.tw/FncNews/stock/64033"
    },
    {
        "title": "個股：普萊德(6263)上半年營收年成長近二成，創歷年同期新高",
        "content": "\n\n \n【往下看更多】\r\n            ►小學生也瘋買股？超狂「家長會長獎」送0050 李兆華大讚\r\n            ►傳台積電加入搶櫃行列 陽明：全力配合重大業務\r\n            ►台股強彈399點該跑？專家曝「3變數」：應適時減碼\n",
        "keywords": [
            "東森財經",
            "fnc",
            "財經新聞",
            "股動錢潮",
            "盤前早報",
            "盤前分析",
            "東森財經新聞",
            "財經粉絲團",
            "趨勢",
            "投顧",
            "即時指數",
            "台股",
            "美股",
            "汽車",
            "房產",
            "理財",
            "投資",
            "職場",
            "產業",
            "EBC",
            "東森電視"
        ],
        "category": "stock",
        "media": "東森財經新聞",
        "datetime": "2021/07/09 12:05",
        "link": "https://fnc.ebc.net.tw/fncnews/stock/137198"
    },
    {
        "title": "個股：聚陽滿單到明年Q1，惟後市轉保守，明年靠客戶、產品再衝兩位數成長",
        "content": "\n\n \n【往下看更多】\r\n            ►小學生也瘋買股？超狂「家長會長獎」送0050 李兆華大讚\r\n            ►傳台積電加入搶櫃行列 陽明：全力配合重大業務\r\n            ►台股強彈399點該跑？專家曝「3變數」：應適時減碼\n",
        "keywords": [
            "東森財經",
            "fnc",
            "財經新聞",
            "股動錢潮",
            "盤前早報",
            "盤前分析",
            "東森財經新聞",
            "財經粉絲團",
            "趨勢",
            "投顧",
            "即時指數",
            "台股",
            "美股",
            "汽車",
            "房產",
            "理財",
            "投資",
            "職場",
            "產業",
            "EBC",
            "東森電視"
        ],
        "category": "stock",
        "media": "東森財經新聞",
        "datetime": "2021/08/24 14:05",
        "link": "https://fnc.ebc.net.tw/fncnews/content/139437"
    },
    {
        "title": "外資觀點：神盾明年仍面臨轉型困境，美系外資調降目標價至100元，重申減碼",
        "content": "\n\n \n【往下看更多】\r\n            ►小學生也瘋買股？超狂「家長會長獎」送0050 李兆華大讚\r\n            ►傳台積電加入搶櫃行列 陽明：全力配合重大業務\r\n            ►台股強彈399點該跑？專家曝「3變數」：應適時減碼\n",
        "keywords": [
            "東森財經",
            "fnc",
            "財經新聞",
            "股動錢潮",
            "盤前早報",
            "盤前分析",
            "東森財經新聞",
            "財經粉絲團",
            "趨勢",
            "投顧",
            "即時指數",
            "台股",
            "美股",
            "汽車",
            "房產",
            "理財",
            "投資",
            "職場",
            "產業",
            "EBC",
            "東森電視"
        ],
        "category": "stock",
        "media": "東森財經新聞",
        "datetime": "2021/08/17 12:05",
        "link": "https://fnc.ebc.net.tw/fncnews/stock/139077"
    },
    {
        "title": "個股：深化物聯網佈局，研華(2395)宣布採用AWS打造端到雲物聯網解決方案",
        "content": "\n\n \n【往下看更多】\r\n            ►小學生也瘋買股？超狂「家長會長獎」送0050 李兆華大讚\r\n            ►傳台積電加入搶櫃行列 陽明：全力配合重大業務\r\n            ►台股強彈399點該跑？專家曝「3變數」：應適時減碼\n",
        "keywords": [
            "東森財經",
            "fnc",
            "財經新聞",
            "股動錢潮",
            "盤前早報",
            "盤前分析",
            "東森財經新聞",
            "財經粉絲團",
            "趨勢",
            "投顧",
            "即時指數",
            "台股",
            "美股",
            "汽車",
            "房產",
            "理財",
            "投資",
            "職場",
            "產業",
            "EBC",
            "東森電視"
        ],
        "category": "stock",
        "media": "東森財經新聞",
        "datetime": "2021/08/24 12:05",
        "link": "https://fnc.ebc.net.tw/fncnews/stock/139421"
    },
    {
        "title": "個股：威宏-KY(8442)7月營收站19個月新高，疫後展望轉趨樂觀",
        "content": "\n\n \n【往下看更多】\r\n            ►小學生也瘋買股？超狂「家長會長獎」送0050 李兆華大讚\r\n            ►傳台積電加入搶櫃行列 陽明：全力配合重大業務\r\n            ►台股強彈399點該跑？專家曝「3變數」：應適時減碼\n",
        "keywords": [
            "東森財經",
            "fnc",
            "財經新聞",
            "股動錢潮",
            "盤前早報",
            "盤前分析",
            "東森財經新聞",
            "財經粉絲團",
            "趨勢",
            "投顧",
            "即時指數",
            "台股",
            "美股",
            "汽車",
            "房產",
            "理財",
            "投資",
            "職場",
            "產業",
            "EBC",
            "東森電視"
        ],
        "category": "stock",
        "media": "東森財經新聞",
        "datetime": "2021/08/11 14:05",
        "link": "https://fnc.ebc.net.tw/fncnews/stock/138830"
    },
    {
        "title": "國內財經：車市復甦，證交所今起三天舉辦「汽車供應鏈」主題式業績發表會",
        "content": "\n\n \n【往下看更多】\r\n            ►五倍券再加碼！2縣市霸氣發現金 5000元月底直接入帳\r\n            ►桃園3人打高端不適 衛生局曝原因：都有1共同點\r\n            ►剛打完高端！20多歲女「突倒地」 30多歲男癱軟嘔吐\n",
        "keywords": [
            "東森財經",
            "fnc",
            "財經新聞",
            "股動錢潮",
            "盤前早報",
            "盤前分析",
            "東森財經新聞",
            "財經粉絲團",
            "趨勢",
            "投顧",
            "即時指數",
            "台股",
            "美股",
            "汽車",
            "房產",
            "理財",
            "投資",
            "職場",
            "產業",
            "EBC",
            "東森電視"
        ],
        "category": "headline",
        "media": "東森財經新聞",
        "datetime": "2021/08/24 14:05",
        "link": "https://fnc.ebc.net.tw/fncnews/content/139435"
    },
    {
        "title": "未上市：連展投控旗下連訊通訊(6820)送件申請登興櫃，109年EPS 1.13元",
        "content": "\n\n \n【往下看更多】\r\n            ►全民上戰場就能贏？退役美軍士官憂：國軍訓練仍在1970水準\r\n            ►產業：BDI指數衝上4000大關，激勵散裝族群盤中大漲，新興、裕民等個股漲停\r\n            ►興櫃：北極星藥業-KY(6550)將啟動全球首個基因標記肝癌三期臨床試驗\n",
        "keywords": [
            "東森財經",
            "fnc",
            "財經新聞",
            "股動錢潮",
            "盤前早報",
            "盤前分析",
            "東森財經新聞",
            "財經粉絲團",
            "趨勢",
            "投顧",
            "即時指數",
            "台股",
            "美股",
            "汽車",
            "房產",
            "理財",
            "投資",
            "職場",
            "產業",
            "EBC",
            "東森電視"
        ],
        "category": "else",
        "media": "東森財經新聞",
        "datetime": "2021/03/12 11:05",
        "link": "https://fnc.ebc.net.tw/fncnews/else/131990"
    },
    {
        "title": "個股：勝一(1773)、中華化(1727)搶攻電子化學品，上半年獲利穩中透堅",
        "content": "\n\n \n【往下看更多】\r\n            ►小學生也瘋買股？超狂「家長會長獎」送0050 李兆華大讚\r\n            ►傳台積電加入搶櫃行列 陽明：全力配合重大業務\r\n            ►台股強彈399點該跑？專家曝「3變數」：應適時減碼\n",
        "keywords": [
            "東森財經",
            "fnc",
            "財經新聞",
            "股動錢潮",
            "盤前早報",
            "盤前分析",
            "東森財經新聞",
            "財經粉絲團",
            "趨勢",
            "投顧",
            "即時指數",
            "台股",
            "美股",
            "汽車",
            "房產",
            "理財",
            "投資",
            "職場",
            "產業",
            "EBC",
            "東森電視"
        ],
        "category": "stock",
        "media": "東森財經新聞",
        "datetime": "2021/08/19 14:05",
        "link": "https://fnc.ebc.net.tw/fncnews/stock/139222"
    },
    {
        "title": "個股：藥華藥(6446)P1101新冠三期臨床獲准，五家醫院啟動收案",
        "content": "\n\n \n【往下看更多】\r\n            ►小學生也瘋買股？超狂「家長會長獎」送0050 李兆華大讚\r\n            ►傳台積電加入搶櫃行列 陽明：全力配合重大業務\r\n            ►台股強彈399點該跑？專家曝「3變數」：應適時減碼\n",
        "keywords": [
            "東森財經",
            "fnc",
            "財經新聞",
            "股動錢潮",
            "盤前早報",
            "盤前分析",
            "東森財經新聞",
            "財經粉絲團",
            "趨勢",
            "投顧",
            "即時指數",
            "台股",
            "美股",
            "汽車",
            "房產",
            "理財",
            "投資",
            "職場",
            "產業",
            "EBC",
            "東森電視"
        ],
        "category": "stock",
        "media": "東森財經新聞",
        "datetime": "2021/08/26 09:05",
        "link": "https://fnc.ebc.net.tw/fncnews/content/139540"
    },
    {
        "title": "個股：中華電(2412)攜手耀登(3138)，成立亞洲首座O-RAN聯盟認證OTIC實驗室",
        "content": "\n\n \n【往下看更多】\r\n            ►小學生也瘋買股？超狂「家長會長獎」送0050 李兆華大讚\r\n            ►傳台積電加入搶櫃行列 陽明：全力配合重大業務\r\n            ►台股強彈399點該跑？專家曝「3變數」：應適時減碼\n",
        "keywords": [
            "東森財經",
            "fnc",
            "財經新聞",
            "股動錢潮",
            "盤前早報",
            "盤前分析",
            "東森財經新聞",
            "財經粉絲團",
            "趨勢",
            "投顧",
            "即時指數",
            "台股",
            "美股",
            "汽車",
            "房產",
            "理財",
            "投資",
            "職場",
            "產業",
            "EBC",
            "東森電視"
        ],
        "category": "stock",
        "media": "東森財經新聞",
        "datetime": "2021/08/26 09:05",
        "link": "https://fnc.ebc.net.tw/fncnews/stock/139539"
    },
    {
        "title": "個股：醫用NBR乳膠需求暢旺，申豐(6582)、南帝(2108)Q2獲利續創佳績",
        "content": "\n\n \n【往下看更多】\r\n            ►小學生也瘋買股？超狂「家長會長獎」送0050 李兆華大讚\r\n            ►傳台積電加入搶櫃行列 陽明：全力配合重大業務\r\n            ►台股強彈399點該跑？專家曝「3變數」：應適時減碼\n",
        "keywords": [
            "東森財經",
            "fnc",
            "財經新聞",
            "股動錢潮",
            "盤前早報",
            "盤前分析",
            "東森財經新聞",
            "財經粉絲團",
            "趨勢",
            "投顧",
            "即時指數",
            "台股",
            "美股",
            "汽車",
            "房產",
            "理財",
            "投資",
            "職場",
            "產業",
            "EBC",
            "東森電視"
        ],
        "category": "stock",
        "media": "東森財經新聞",
        "datetime": "2021/08/10 13:05",
        "link": "https://fnc.ebc.net.tw/fncnews/stock/138756"
    },
    {
        "title": "個股：旭然(4556)越南廠首季裝機完成，今年營運增添動能",
        "content": "\n\n \n【往下看更多】\r\n            ►小學生也瘋買股？超狂「家長會長獎」送0050 李兆華大讚\r\n            ►傳台積電加入搶櫃行列 陽明：全力配合重大業務\r\n            ►台股強彈399點該跑？專家曝「3變數」：應適時減碼\n",
        "keywords": [
            "東森財經",
            "fnc",
            "財經新聞",
            "股動錢潮",
            "盤前早報",
            "盤前分析",
            "東森財經新聞",
            "財經粉絲團",
            "趨勢",
            "投顧",
            "即時指數",
            "台股",
            "美股",
            "汽車",
            "房產",
            "理財",
            "投資",
            "職場",
            "產業",
            "EBC",
            "東森電視"
        ],
        "category": "stock",
        "media": "東森財經新聞",
        "datetime": "2021/02/20 11:05",
        "link": "https://fnc.ebc.net.tw/fncnews/stock/131444"
    },
    {
        "title": "金控領漲撐盤 元大金重摔近7％？ 專家：當沖量縮衝擊",
        "content": "\n\n \n【往下看更多】\r\n            ►航運、電子咕嚕咕嚕 台股量縮失守季線 網哀一片：人走茶涼\r\n            ►小資女跟風當航海王「賠掉1年薪水」 想靠電子股翻身更慘\r\n            ►5倍券變6倍！陳其邁加碼發千元「高雄券」細節曝光\n",
        "keywords": [
            "台股",
            "金控",
            "元大金",
            "證券業",
            "當沖降稅"
        ],
        "category": "stock",
        "media": "東森財經新聞",
        "datetime": "2021/08/11 13:05",
        "link": "https://fnc.ebc.net.tw/fncnews/stock/138819"
    },
    {
        "title": "個股：國際品牌廠拉貨強勁，八貫Q2稅後淨利創歷年同期新高，EPS 0.84元",
        "content": "\n\n \n【往下看更多】\r\n            ►小學生也瘋買股？超狂「家長會長獎」送0050 李兆華大讚\r\n            ►傳台積電加入搶櫃行列 陽明：全力配合重大業務\r\n            ►台股強彈399點該跑？專家曝「3變數」：應適時減碼\n",
        "keywords": [
            "東森財經",
            "fnc",
            "財經新聞",
            "股動錢潮",
            "盤前早報",
            "盤前分析",
            "東森財經新聞",
            "財經粉絲團",
            "趨勢",
            "投顧",
            "即時指數",
            "台股",
            "美股",
            "汽車",
            "房產",
            "理財",
            "投資",
            "職場",
            "產業",
            "EBC",
            "東森電視"
        ],
        "category": "stock",
        "media": "東森財經新聞",
        "datetime": "2021/08/11 11:05",
        "link": "https://fnc.ebc.net.tw/fncnews/stock/138805"
    },
    {
        "title": "個股：手機拉貨旺季＋解封消費性買氣回籠，亞電(4939)後續展望轉趨樂觀",
        "content": "\n\n \n【往下看更多】\r\n            ►小學生也瘋買股？超狂「家長會長獎」送0050 李兆華大讚\r\n            ►傳台積電加入搶櫃行列 陽明：全力配合重大業務\r\n            ►台股強彈399點該跑？專家曝「3變數」：應適時減碼\n",
        "keywords": [
            "東森財經",
            "fnc",
            "財經新聞",
            "股動錢潮",
            "盤前早報",
            "盤前分析",
            "東森財經新聞",
            "財經粉絲團",
            "趨勢",
            "投顧",
            "即時指數",
            "台股",
            "美股",
            "汽車",
            "房產",
            "理財",
            "投資",
            "職場",
            "產業",
            "EBC",
            "東森電視"
        ],
        "category": "stock",
        "media": "東森財經新聞",
        "datetime": "2021/07/06 12:05",
        "link": "https://fnc.ebc.net.tw/fncnews/stock/136986"
    },
    {
        "title": "個股：合富-KY(4745)上半年EPS 3.22元，下半年業績成長續拚三成",
        "content": "\n\n \n【往下看更多】\r\n            ►小學生也瘋買股？超狂「家長會長獎」送0050 李兆華大讚\r\n            ►傳台積電加入搶櫃行列 陽明：全力配合重大業務\r\n            ►台股強彈399點該跑？專家曝「3變數」：應適時減碼\n",
        "keywords": [
            "東森財經",
            "fnc",
            "財經新聞",
            "股動錢潮",
            "盤前早報",
            "盤前分析",
            "東森財經新聞",
            "財經粉絲團",
            "趨勢",
            "投顧",
            "即時指數",
            "台股",
            "美股",
            "汽車",
            "房產",
            "理財",
            "投資",
            "職場",
            "產業",
            "EBC",
            "東森電視"
        ],
        "category": "stock",
        "media": "東森財經新聞",
        "datetime": "2019/08/05 14:04",
        "link": "https://fnc.ebc.net.tw/FncNews/stock/94540"
    },
    {
        "title": "產業：2021 Touch Taiwan下週三登場，面板雙虎領軍，鎖定跨域整合應用",
        "content": "\n\n \n【往下看更多】\r\n            ►全民上戰場就能贏？退役美軍士官憂：國軍訓練仍在1970水準\r\n            ►產業：BDI指數衝上4000大關，激勵散裝族群盤中大漲，新興、裕民等個股漲停\r\n            ►興櫃：北極星藥業-KY(6550)將啟動全球首個基因標記肝癌三期臨床試驗\n",
        "keywords": [
            "東森財經",
            "fnc",
            "財經新聞",
            "股動錢潮",
            "盤前早報",
            "盤前分析",
            "東森財經新聞",
            "財經粉絲團",
            "趨勢",
            "投顧",
            "即時指數",
            "台股",
            "美股",
            "汽車",
            "房產",
            "理財",
            "投資",
            "職場",
            "產業",
            "EBC",
            "東森電視"
        ],
        "category": "else",
        "media": "東森財經新聞",
        "datetime": "2021/04/14 13:05",
        "link": "https://fnc.ebc.net.tw/fncnews/else/133058"
    },
    {
        "title": "個股：佳世達(2352)7月營收187億元，年增三成，8月12日召開線上法說",
        "content": "\n\n \n【往下看更多】\r\n            ►小學生也瘋買股？超狂「家長會長獎」送0050 李兆華大讚\r\n            ►傳台積電加入搶櫃行列 陽明：全力配合重大業務\r\n            ►台股強彈399點該跑？專家曝「3變數」：應適時減碼\n",
        "keywords": [
            "東森財經",
            "fnc",
            "財經新聞",
            "股動錢潮",
            "盤前早報",
            "盤前分析",
            "東森財經新聞",
            "財經粉絲團",
            "趨勢",
            "投顧",
            "即時指數",
            "台股",
            "美股",
            "汽車",
            "房產",
            "理財",
            "投資",
            "職場",
            "產業",
            "EBC",
            "東森電視"
        ],
        "category": "stock",
        "media": "東森財經新聞",
        "datetime": "2021/08/05 10:05",
        "link": "https://fnc.ebc.net.tw/fncnews/stock/138524"
    },
    {
        "title": "個股：ICT事業優化，聯合艦隊發揮綜效，佳世達前5月營收864億元，年增28%",
        "content": "\n\n \n【往下看更多】\r\n            ►小學生也瘋買股？超狂「家長會長獎」送0050 李兆華大讚\r\n            ►傳台積電加入搶櫃行列 陽明：全力配合重大業務\r\n            ►台股強彈399點該跑？專家曝「3變數」：應適時減碼\n",
        "keywords": [
            "東森財經",
            "fnc",
            "財經新聞",
            "股動錢潮",
            "盤前早報",
            "盤前分析",
            "東森財經新聞",
            "財經粉絲團",
            "趨勢",
            "投顧",
            "即時指數",
            "台股",
            "美股",
            "汽車",
            "房產",
            "理財",
            "投資",
            "職場",
            "產業",
            "EBC",
            "東森電視"
        ],
        "category": "stock",
        "media": "東森財經新聞",
        "datetime": "2021/06/04 13:05",
        "link": "https://fnc.ebc.net.tw/fncnews/stock/135535"
    },
    {
        "title": "個股：環瑞醫更名拚轉骨，將跨醫療耗材，角膜塑型片拚明年送件申請上市",
        "content": "\n\n \n【往下看更多】\r\n            ►小學生也瘋買股？超狂「家長會長獎」送0050 李兆華大讚\r\n            ►傳台積電加入搶櫃行列 陽明：全力配合重大業務\r\n            ►台股強彈399點該跑？專家曝「3變數」：應適時減碼\n",
        "keywords": [
            "東森財經",
            "fnc",
            "財經新聞",
            "股動錢潮",
            "盤前早報",
            "盤前分析",
            "東森財經新聞",
            "財經粉絲團",
            "趨勢",
            "投顧",
            "即時指數",
            "台股",
            "美股",
            "汽車",
            "房產",
            "理財",
            "投資",
            "職場",
            "產業",
            "EBC",
            "東森電視"
        ],
        "category": "stock",
        "media": "東森財經新聞",
        "datetime": "2020/08/28 14:05",
        "link": "https://fnc.ebc.net.tw/FncNews/stock/124378"
    },
    {
        "title": "個股：宏正(6277)垂直市場布局發酵，下半年展望維持正向",
        "content": "\n\n \n【往下看更多】\r\n            ►小學生也瘋買股？超狂「家長會長獎」送0050 李兆華大讚\r\n            ►傳台積電加入搶櫃行列 陽明：全力配合重大業務\r\n            ►台股強彈399點該跑？專家曝「3變數」：應適時減碼\n",
        "keywords": [
            "東森財經",
            "fnc",
            "財經新聞",
            "股動錢潮",
            "盤前早報",
            "盤前分析",
            "東森財經新聞",
            "財經粉絲團",
            "趨勢",
            "投顧",
            "即時指數",
            "台股",
            "美股",
            "汽車",
            "房產",
            "理財",
            "投資",
            "職場",
            "產業",
            "EBC",
            "東森電視"
        ],
        "category": "stock",
        "media": "東森財經新聞",
        "datetime": "2021/08/12 10:05",
        "link": "https://fnc.ebc.net.tw/fncnews/content/138867"
    },
    {
        "title": "個股：宏正(6277)Q2獲利估持穩，下半年營運拚轉強",
        "content": "\n\n \n【往下看更多】\r\n            ►小學生也瘋買股？超狂「家長會長獎」送0050 李兆華大讚\r\n            ►傳台積電加入搶櫃行列 陽明：全力配合重大業務\r\n            ►台股強彈399點該跑？專家曝「3變數」：應適時減碼\n",
        "keywords": [
            "東森財經",
            "fnc",
            "財經新聞",
            "股動錢潮",
            "盤前早報",
            "盤前分析",
            "東森財經新聞",
            "財經粉絲團",
            "趨勢",
            "投顧",
            "即時指數",
            "台股",
            "美股",
            "汽車",
            "房產",
            "理財",
            "投資",
            "職場",
            "產業",
            "EBC",
            "東森電視"
        ],
        "category": "stock",
        "media": "東森財經新聞",
        "datetime": "2021/08/02 13:05",
        "link": "https://fnc.ebc.net.tw/fncnews/stock/138349"
    },
    {
        "title": "個股：欣天然(9918)供氣戶數35萬戶達陣，今年新增用戶目標為4200戶",
        "content": "\n\n \n【往下看更多】\r\n            ►小學生也瘋買股？超狂「家長會長獎」送0050 李兆華大讚\r\n            ►傳台積電加入搶櫃行列 陽明：全力配合重大業務\r\n            ►台股強彈399點該跑？專家曝「3變數」：應適時減碼\n",
        "keywords": [
            "東森財經",
            "fnc",
            "財經新聞",
            "股動錢潮",
            "盤前早報",
            "盤前分析",
            "東森財經新聞",
            "財經粉絲團",
            "趨勢",
            "投顧",
            "即時指數",
            "台股",
            "美股",
            "汽車",
            "房產",
            "理財",
            "投資",
            "職場",
            "產業",
            "EBC",
            "東森電視"
        ],
        "category": "stock",
        "media": "東森財經新聞",
        "datetime": "2020/06/29 09:05",
        "link": "https://fnc.ebc.net.tw/FncNews/stock/121538"
    },
    {
        "title": "個股：玩家需求殷，顯卡供給仍缺，法人喊買微星、技嘉",
        "content": "\n\n \n【往下看更多】\r\n            ►小學生也瘋買股？超狂「家長會長獎」送0050 李兆華大讚\r\n            ►傳台積電加入搶櫃行列 陽明：全力配合重大業務\r\n            ►台股強彈399點該跑？專家曝「3變數」：應適時減碼\n",
        "keywords": [
            "東森財經",
            "fnc",
            "財經新聞",
            "股動錢潮",
            "盤前早報",
            "盤前分析",
            "東森財經新聞",
            "財經粉絲團",
            "趨勢",
            "投顧",
            "即時指數",
            "台股",
            "美股",
            "汽車",
            "房產",
            "理財",
            "投資",
            "職場",
            "產業",
            "EBC",
            "東森電視"
        ],
        "category": "stock",
        "media": "東森財經新聞",
        "datetime": "2021/08/23 14:05",
        "link": "https://fnc.ebc.net.tw/fncnews/stock/139362"
    },
    {
        "title": "個股：訊連(5203)獲威聯通採用，打造智慧人臉辨識解決方案",
        "content": "\n\n \n【往下看更多】\r\n            ►小學生也瘋買股？超狂「家長會長獎」送0050 李兆華大讚\r\n            ►傳台積電加入搶櫃行列 陽明：全力配合重大業務\r\n            ►台股強彈399點該跑？專家曝「3變數」：應適時減碼\n",
        "keywords": [
            "東森財經",
            "fnc",
            "財經新聞",
            "股動錢潮",
            "盤前早報",
            "盤前分析",
            "東森財經新聞",
            "財經粉絲團",
            "趨勢",
            "投顧",
            "即時指數",
            "台股",
            "美股",
            "汽車",
            "房產",
            "理財",
            "投資",
            "職場",
            "產業",
            "EBC",
            "東森電視"
        ],
        "category": "stock",
        "media": "東森財經新聞",
        "datetime": "2021/08/23 09:05",
        "link": "https://fnc.ebc.net.tw/fncnews/content/139322"
    },
    {
        "title": "個股：五倍券將上路，3C大賣場提前鳴槍，順發、全國電、燦坤H2業績吞補",
        "content": "\n\n \n【往下看更多】\r\n            ►小學生也瘋買股？超狂「家長會長獎」送0050 李兆華大讚\r\n            ►傳台積電加入搶櫃行列 陽明：全力配合重大業務\r\n            ►台股強彈399點該跑？專家曝「3變數」：應適時減碼\n",
        "keywords": [
            "東森財經",
            "fnc",
            "財經新聞",
            "股動錢潮",
            "盤前早報",
            "盤前分析",
            "東森財經新聞",
            "財經粉絲團",
            "趨勢",
            "投顧",
            "即時指數",
            "台股",
            "美股",
            "汽車",
            "房產",
            "理財",
            "投資",
            "職場",
            "產業",
            "EBC",
            "東森電視"
        ],
        "category": "stock",
        "media": "東森財經新聞",
        "datetime": "2021/08/20 09:05",
        "link": "https://fnc.ebc.net.tw/fncnews/stock/139248"
    },
    {
        "title": "個股：遠距商機激勵，順發(6154)上季獲利狂噴20倍，上半年EPS達0.9元",
        "content": "\n\n \n【往下看更多】\r\n            ►小學生也瘋買股？超狂「家長會長獎」送0050 李兆華大讚\r\n            ►傳台積電加入搶櫃行列 陽明：全力配合重大業務\r\n            ►台股強彈399點該跑？專家曝「3變數」：應適時減碼\n",
        "keywords": [
            "東森財經",
            "fnc",
            "財經新聞",
            "股動錢潮",
            "盤前早報",
            "盤前分析",
            "東森財經新聞",
            "財經粉絲團",
            "趨勢",
            "投顧",
            "即時指數",
            "台股",
            "美股",
            "汽車",
            "房產",
            "理財",
            "投資",
            "職場",
            "產業",
            "EBC",
            "東森電視"
        ],
        "category": "stock",
        "media": "東森財經新聞",
        "datetime": "2021/07/21 12:05",
        "link": "https://fnc.ebc.net.tw/fncnews/stock/137787"
    },
    {
        "title": "個股：立隆電Q2獲利創單季新高，上半年每股賺2.81元，Q3營運再戰新高點",
        "content": "\n\n \n【往下看更多】\r\n            ►小學生也瘋買股？超狂「家長會長獎」送0050 李兆華大讚\r\n            ►傳台積電加入搶櫃行列 陽明：全力配合重大業務\r\n            ►台股強彈399點該跑？專家曝「3變數」：應適時減碼\n",
        "keywords": [
            "東森財經",
            "fnc",
            "財經新聞",
            "股動錢潮",
            "盤前早報",
            "盤前分析",
            "東森財經新聞",
            "財經粉絲團",
            "趨勢",
            "投顧",
            "即時指數",
            "台股",
            "美股",
            "汽車",
            "房產",
            "理財",
            "投資",
            "職場",
            "產業",
            "EBC",
            "東森電視"
        ],
        "category": "stock",
        "media": "東森財經新聞",
        "datetime": "2021/08/12 12:05",
        "link": "https://fnc.ebc.net.tw/fncnews/content/138878"
    },
    {
        "title": "個股：劍麟(2228)Q2轉虧為盈，上半年每股盈餘2.22元",
        "content": "\n\n \n【往下看更多】\r\n            ►小學生也瘋買股？超狂「家長會長獎」送0050 李兆華大讚\r\n            ►傳台積電加入搶櫃行列 陽明：全力配合重大業務\r\n            ►台股強彈399點該跑？專家曝「3變數」：應適時減碼\n",
        "keywords": [
            "東森財經",
            "fnc",
            "財經新聞",
            "股動錢潮",
            "盤前早報",
            "盤前分析",
            "東森財經新聞",
            "財經粉絲團",
            "趨勢",
            "投顧",
            "即時指數",
            "台股",
            "美股",
            "汽車",
            "房產",
            "理財",
            "投資",
            "職場",
            "產業",
            "EBC",
            "東森電視"
        ],
        "category": "stock",
        "media": "東森財經新聞",
        "datetime": "2021/08/05 09:05",
        "link": "https://fnc.ebc.net.tw/fncnews/stock/138514"
    },
    {
        "title": "個股：宇隆(2233)Q2獲利優於預期，每股盈餘2.33元，股價陷入貼息窘境",
        "content": "\n\n \n【往下看更多】\r\n            ►全民上戰場就能贏？退役美軍士官憂：國軍訓練仍在1970水準\r\n            ►產業：BDI指數衝上4000大關，激勵散裝族群盤中大漲，新興、裕民等個股漲停\r\n            ►興櫃：北極星藥業-KY(6550)將啟動全球首個基因標記肝癌三期臨床試驗\n",
        "keywords": [
            "東森財經",
            "fnc",
            "財經新聞",
            "股動錢潮",
            "盤前早報",
            "盤前分析",
            "東森財經新聞",
            "財經粉絲團",
            "趨勢",
            "投顧",
            "即時指數",
            "台股",
            "美股",
            "汽車",
            "房產",
            "理財",
            "投資",
            "職場",
            "產業",
            "EBC",
            "東森電視"
        ],
        "category": "else",
        "media": "東森財經新聞",
        "datetime": "2021/08/19 11:05",
        "link": "https://fnc.ebc.net.tw/fncnews/else/139201"
    }
]
